{
    "env": {
        "example": 2,
        "border_rule": "stay"
    },
    "play": {
        "num_samples": 10000,
        "max_steps": 6
    },
    "agents": [
        {
            "method": "dn",
            "name": "dn_g0,01",
            "n_hidden": 16,
            "lr": 0.00005,
            "gamma": 0.01
        },{
            "method": "dn",
            "name": "dn_g0,1",
            "n_hidden": 16,
            "lr": 0.00005,
            "gamma": 0.1
        },{
            "method": "dn",
            "name": "dn_g0,8",
            "n_hidden": 16,
            "lr": 0.00005,
            "gamma": 0.8
        },{
            "method": "dn",
            "name": "dn_g0,95",
            "n_hidden": 16,
            "lr": 0.00005,
            "gamma": 0.95
        },{
            "method": "dn",
            "name": "dn_g0,99",
            "n_hidden": 16,
            "lr": 0.00005,
            "gamma": 0.99
        }
    ]
}